agentsite/__init__.py
agentsite/cli.py
agentsite/config.py
agentsite/models.py
agentsite/agents/__init__.py
agentsite/agents/designer.py
agentsite/agents/developer.py
agentsite/agents/orchestrator.py
agentsite/agents/personas.py
agentsite/agents/pm.py
agentsite/agents/reviewer.py
agentsite/agents/tools.py
agentsite/api/__init__.py
agentsite/api/app.py
agentsite/api/deps.py
agentsite/api/websocket.py
agentsite/api/routes/__init__.py
agentsite/api/routes/agents.py
agentsite/api/routes/assets.py
agentsite/api/routes/generate.py
agentsite/api/routes/models.py
agentsite/api/routes/preview.py
agentsite/api/routes/projects.py
agentsite/api/routes/providers.py
agentsite/engine/__init__.py
agentsite/engine/asset_handler.py
agentsite/engine/gemini_patch.py
agentsite/engine/pipeline.py
agentsite/engine/project_manager.py
agentsite/storage/__init__.py
agentsite/storage/database.py
agentsite/storage/repository.py
agentsite-0.1.0.dist-info/METADATA
agentsite-0.1.0.dist-info/WHEEL
agentsite-0.1.0.dist-info/entry_points.txt
agentsite-0.1.0.dist-info/top_level.txt
agentsite-0.1.0.dist-info/RECORD
