Metadata-Version: 2.4
Name: agentsite
Version: 0.1.0
Summary: AI-Powered Website Builder using Prompture agent orchestration
Author-email: Juan Denis <juan@vene.co>
License-Expression: MIT
Classifier: Programming Language :: Python :: 3
Classifier: Operating System :: OS Independent
Requires-Python: >=3.10
Requires-Dist: prompture>=0.0.40
Requires-Dist: fastapi>=0.100
Requires-Dist: uvicorn[standard]>=0.20
Requires-Dist: aiosqlite>=0.19
Requires-Dist: click>=8.0
Requires-Dist: pydantic>=2.0
Requires-Dist: pydantic-settings>=2.0
Requires-Dist: python-dotenv>=0.19.0
Requires-Dist: python-multipart>=0.0.6
Provides-Extra: test
Requires-Dist: pytest>=7.0; extra == "test"
Requires-Dist: pytest-asyncio>=0.23.0; extra == "test"
Requires-Dist: httpx>=0.25.0; extra == "test"
Provides-Extra: dev
Requires-Dist: pytest>=7.0; extra == "dev"
Requires-Dist: pytest-asyncio>=0.23.0; extra == "dev"
Requires-Dist: httpx>=0.25.0; extra == "dev"
Requires-Dist: ruff>=0.8.0; extra == "dev"
